<?xml version="1.0" encoding="UTF-8"?>
<list xmlns:xsi="http://www.w3.org/2001/XMLSchema-instance" xsi:noNamespaceSchemaLocation="../../xsd/skills.xsd">
	<skill id="8500" levels="1" name="핑크 탈리스만 - CON">
		<!-- Confirmed CT2.5 -->
		<set name="magicLvl" val="55" />
		<set name="operateType" val="P" />
		<set name="target" val="TARGET_SELF" />
		<for>
			<add order="0x10" stat="CON" val="2" />
		</for>
	</skill>
	<skill id="8501" levels="1" name="핑크 탈리스만 - INT">
		<!-- Confirmed CT2.5 -->
		<set name="magicLvl" val="55" />
		<set name="operateType" val="P" />
		<set name="target" val="TARGET_SELF" />
		<for>
			<add order="0x10" stat="INT" val="2" />
		</for>
	</skill>
	<skill id="8502" levels="1" name="핑크 탈리스만 - WIT">
		<!-- Confirmed CT2.5 -->
		<set name="magicLvl" val="55" />
		<set name="operateType" val="P" />
		<set name="target" val="TARGET_SELF" />
		<for>
			<add order="0x10" stat="WIT" val="2" />
		</for>
	</skill>
	<skill id="8503" levels="1" name="핑크 탈리스만 - MEN">
		<!-- Confirmed CT2.5 -->
		<set name="magicLvl" val="55" />
		<set name="operateType" val="P" />
		<set name="target" val="TARGET_SELF" />
		<for>
			<add order="0x10" stat="MEN" val="2" />
		</for>
	</skill>
	<skill id="8504" levels="1" name="핑크 탈리스만 - 쇼크 저항">
		<!-- Confirmed CT2.5 -->
		<set name="magicLvl" val="55" />
		<set name="operateType" val="P" />
		<set name="target" val="TARGET_SELF" />
		<for>
			<sub order="0x40" stat="stunVuln" val="15" />
		</for>
	</skill>
	<skill id="8505" levels="1" name="핑크 탈리스만 - 수면 저항">
		<!-- Confirmed CT2.5 -->
		<set name="magicLvl" val="55" />
		<set name="operateType" val="P" />
		<set name="target" val="TARGET_SELF" />
		<for>
			<sub order="0x40" stat="sleepVuln" val="15" />
		</for>
	</skill>
	<skill id="8506" levels="1" name="핑크 탈리스만 - 홀드 저항">
		<!-- Confirmed CT2.5 -->
		<set name="magicLvl" val="55" />
		<set name="operateType" val="P" />
		<set name="target" val="TARGET_SELF" />
		<for>
			<sub order="0x40" stat="rootVuln" val="15" />
		</for>
	</skill>
	<skill id="8507" levels="1" name="핑크 탈리스만 - 마비 저항">
		<!-- Confirmed CT2.5 -->
		<set name="magicLvl" val="55" />
		<set name="operateType" val="P" />
		<set name="target" val="TARGET_SELF" />
		<for>
			<sub order="0x40" stat="paralyzeVuln" val="15" />
		</for>
	</skill>
	<skill id="8508" levels="1" name="핑크 탈리스만 - All STAT">
		<!-- Confirmed CT2.5 -->
		<set name="magicLvl" val="55" />
		<set name="operateType" val="P" />
		<set name="target" val="TARGET_SELF" />
		<for>
			<add order="0x10" stat="STR" val="1" />
			<add order="0x10" stat="DEX" val="1" />
			<add order="0x10" stat="CON" val="1" />
			<add order="0x10" stat="INT" val="1" />
			<add order="0x10" stat="WIT" val="1" />
			<add order="0x10" stat="MEN" val="1" />
		</for>
	</skill>
	<skill id="8509" levels="1" name="축복받은 귀환의 능력">
		<set name="isMagic" val="2" /> <!-- Static Skill -->
		<set name="target" val="TARGET_NONE" />
		<set name="skillType" val="NOTDONE" />
		<set name="operateType" val="A1" />
		<set name="reuseDelay" val="3600000" />
	</skill>
	<skill id="8510" levels="1" name="친구 소환">
		<set name="isMagic" val="2" /> <!-- Static Skill -->
		<set name="target" val="TARGET_NONE" />
		<set name="skillType" val="NOTDONE" />
		<set name="operateType" val="A1" />
		<set name="reuseDelay" val="3600000" />
	</skill>
	<skill id="8511" levels="1" name="승리의 축복">
		<!-- Increases Speed by 2%. -->
		<set name="target" val="TARGET_NONE" />
		<set name="skillType" val="NOTDONE" />
		<set name="operateType" val="P" />
	</skill>
	<skill id="8512" levels="1" name="국가대표 용사의 집념">
		<!-- "When used, you can obtain at random one 3-, 7-, 10-, 30-day, or unlimited National Representative Warrior's accessory set. Upon skill use, 10 Proofs of Cheers are consumed, and it can be cancelled when attacked." -->
		<set name="target" val="TARGET_NONE" />
		<set name="skillType" val="NOTDONE" />
		<set name="operateType" val="P" />
	</skill>
	<skill id="8513" levels="1" name="국가대표 축복의 주문">
		<!-- "When used, you can obtain at random a Blessed Scroll of Escape or a B~S grade Blessed Weapon/Armor Strengthening Scroll. Upon skill use, 10 Proofs of Cheers are consumed, and it can be cancelled when attacked." -->
		<set name="target" val="TARGET_NONE" />
		<set name="skillType" val="NOTDONE" />
		<set name="operateType" val="P" />
	</skill>
	<skill id="8514" levels="1" name="국가대표 승리의 기운">
		<!-- "When used, you can obtain at random one Nevit's Hourglass 1~4 hours and Nevit's Voice. Upon skill use, 10 Proofs of Cheers are consumed, and it can be cancelled when attacked." -->
		<set name="target" val="TARGET_NONE" />
		<set name="skillType" val="NOTDONE" />
		<set name="operateType" val="P" />
	</skill>
	<skill id="8515" levels="1" name="아가시온 봉인 해제 - 볼트래핑 그노시안">
		<!-- Removes the seal of Agathion. -->
		<set name="target" val="TARGET_NONE" />
		<set name="skillType" val="NOTDONE" />
		<set name="operateType" val="P" />
	</skill>
	<skill id="8516" levels="1" name="아가시온 봉인 해제 - 볼트래핑 오로드리엘">
		<!-- Removes the seal of Agathion. -->
		<set name="target" val="TARGET_NONE" />
		<set name="skillType" val="NOTDONE" />
		<set name="operateType" val="P" />
	</skill>
	<skill id="8517" levels="1" name="아가시온 봉인 해제 - 패널티 킥">
		<!-- Removes the seal of Agathion. -->
		<set name="target" val="TARGET_NONE" />
		<set name="skillType" val="NOTDONE" />
		<set name="operateType" val="P" />
	</skill>
	<skill id="8518" levels="1" name="알림이">
		<!-- Informs you of the re-supply time of the gift given by the Agathion. -->
		<set name="target" val="TARGET_NONE" />
		<set name="skillType" val="NOTDONE" />
		<set name="operateType" val="P" />
	</skill>
	<skill id="8519" levels="1" name="알림이">
		<!-- Informs you of the re-supply time of the gift given by the Agathion. -->
		<set name="target" val="TARGET_NONE" />
		<set name="skillType" val="NOTDONE" />
		<set name="operateType" val="P" />
	</skill>
	<skill id="8520" levels="1" name="알림이">
		<!-- Informs you of the re-supply time of the gift given by the Agathion. -->
		<set name="target" val="TARGET_NONE" />
		<set name="skillType" val="NOTDONE" />
		<set name="operateType" val="P" />
	</skill>
	<skill id="8521" levels="1" name="아가시온 봉인해제 - 안타라스">
		<!-- Removes the seal of Agathion. -->
		<set name="isMagic" val="2" /> <!-- Static Skill -->
		<set name="target" val="TARGET_SELF" />
		<set name="skillType" val="AGATHION" />
		<set name="operateType" val="A1" />
		<set name="hitTime" val="3000" />
		<set name="npcId" val="16077" />
	</skill>
	<skill id="8522" levels="1" name="아가시온 봉인해제 - 네비트의 전령 칸나">
		<!-- Removes the seal of Agathion. -->
		<set name="isMagic" val="2" /> <!-- Static Skill -->
		<set name="target" val="TARGET_SELF" />
		<set name="skillType" val="AGATHION" />
		<set name="operateType" val="A1" />
		<set name="hitTime" val="3000" />
		<set name="npcId" val="16078" />
	</skill>
	<skill id="8523" levels="1" name="아가시온 봉인해제 - 여명의 수호자 칼레신">
		<!-- Removes the seal of Agathion. -->
		<set name="isMagic" val="2" /> <!-- Static Skill -->
		<set name="target" val="TARGET_SELF" />
		<set name="skillType" val="AGATHION" />
		<set name="operateType" val="A1" />
		<set name="hitTime" val="3000" />
		<set name="npcId" val="16079" />
	</skill>
	<skill id="8524" levels="1" name="영웅의 신성한 공격">
		<!-- Divine attck is increased by 250. -->
		<set name="target" val="TARGET_NONE" />
		<set name="skillType" val="NOTDONE" />
		<set name="operateType" val="P" />
	</skill>
	<skill id="8525" levels="1" name="영웅의 신성한 공격">
		<!-- Increases holy attack by 250. -->
		<set name="target" val="TARGET_NONE" />
		<set name="skillType" val="NOTDONE" />
		<set name="operateType" val="P" />
	</skill>
	<skill id="8526" levels="1" name="반짝이는 팔찌">
		<!-- 3 Talisman can be equipped. -->
		<set name="target" val="TARGET_NONE" />
		<set name="skillType" val="NOTDONE" />
		<set name="operateType" val="P" />
	</skill>
</list>
