<?xml version="1.0" encoding="UTF-8"?>
<list xmlns:xsi="http://www.w3.org/2001/XMLSchema-instance" xsi:noNamespaceSchemaLocation="../../xsd/items.xsd">
	<item id="600" type="Armor" name="봉인된 아바돈 부츠">
		<set name="icon" val="icon.armor_t66_b_i02" />
		<set name="default_action" val="equip" />
		<set name="bodypart" val="feet" />
		<set name="immediate_effect" val="1" />
		<set name="crystal_count" val="53" />
		<set name="crystal_type" val="b" />
		<set name="material" val="damascus" />
		<set name="weight" val="1170" />
		<set name="price" val="399100" />
		<set name="enchant_enabled" val="1" />
		<for>
			<add order="0x10" stat="pDef" val="41" />
			<enchant order="0x0C" stat="pDef" val="0" />
		</for>
	</item>
	<item id="601" type="Armor" name="봉인된 둠 부츠">
		<set name="icon" val="icon.armor_t71_b_i02" />
		<set name="default_action" val="equip" />
		<set name="bodypart" val="feet" />
		<set name="immediate_effect" val="1" />
		<set name="crystal_count" val="83" />
		<set name="crystal_type" val="b" />
		<set name="material" val="mithril" />
		<set name="weight" val="1130" />
		<set name="price" val="618800" />
		<set name="enchant_enabled" val="1" />
		<for>
			<add order="0x10" stat="pDef" val="44" />
			<enchant order="0x0C" stat="pDef" val="0" />
		</for>
	</item>
	<item id="602" type="Armor" name="맹약의 부츠">
		<set name="icon" val="icon.armor_iron_boots_i00" />
		<set name="default_action" val="equip" />
		<set name="bodypart" val="feet" />
		<set name="immediate_effect" val="1" />
		<set name="crystal_count" val="154" />
		<set name="crystal_type" val="b" />
		<set name="material" val="chrysolite" />
		<set name="weight" val="1130" />
		<set name="price" val="890000" />
		<set name="enchant_enabled" val="1" />
		<for>
			<add order="0x10" stat="pDef" val="45" />
			<enchant order="0x0C" stat="pDef" val="0" />
		</for>
	</item>
	<item id="603" type="Armor" name="디바인 부츠">
		<set name="icon" val="icon.armor_t67_b_i00" />
		<set name="default_action" val="equip" />
		<set name="bodypart" val="feet" />
		<set name="immediate_effect" val="1" />
		<set name="crystal_count" val="143" />
		<set name="crystal_type" val="c" />
		<set name="material" val="adamantaite" />
		<set name="weight" val="1200" />
		<set name="price" val="275100" />
		<set name="enchant_enabled" val="1" />
		<for>
			<add order="0x10" stat="pDef" val="39" />
			<enchant order="0x0C" stat="pDef" val="0" />
		</for>
	</item>
	<item id="604" type="Armor" name="고급 가죽 장갑">
		<set name="icon" val="icon.armor_t09_g_i00" />
		<set name="default_action" val="equip" />
		<set name="bodypart" val="gloves" />
		<set name="immediate_effect" val="1" />
		<set name="crystal_count" val="30" />
		<set name="crystal_type" val="d" />
		<set name="material" val="leather" />
		<set name="weight" val="650" />
		<set name="price" val="16100" />
		<set name="enchant_enabled" val="1" />
		<for>
			<add order="0x10" stat="pDef" val="19" />
			<enchant order="0x0C" stat="pDef" val="0" />
		</for>
	</item>
	<item id="605" type="Armor" name="가죽 건틀렛">
		<set name="icon" val="icon.armor_t18_g_i00" />
		<set name="default_action" val="equip" />
		<set name="bodypart" val="gloves" />
		<set name="immediate_effect" val="1" />
		<set name="crystal_count" val="47" />
		<set name="crystal_type" val="d" />
		<set name="material" val="leather" />
		<set name="weight" val="640" />
		<set name="price" val="25600" />
		<set name="enchant_enabled" val="1" />
		<for>
			<add order="0x10" stat="pDef" val="22" />
			<enchant order="0x0C" stat="pDef" val="0" />
		</for>
	</item>
	<item id="606" type="Armor" name="진혼의 건틀렛">
		<set name="icon" val="icon.armor_t40_g_i00" />
		<set name="default_action" val="equip" />
		<set name="bodypart" val="gloves" />
		<set name="immediate_effect" val="1" />
		<set name="crystal_count" val="106" />
		<set name="crystal_type" val="d" />
		<set name="material" val="leather" />
		<set name="weight" val="630" />
		<set name="price" val="57400" />
		<set name="enchant_enabled" val="1" />
		<for>
			<add order="0x10" stat="pDef" val="27" />
			<enchant order="0x0C" stat="pDef" val="0" />
		</for>
	</item>
	<item id="607" type="Armor" name="오거 파워 건틀렛">
		<set name="icon" val="icon.armor_t45_g_i00" />
		<set name="default_action" val="equip" />
		<set name="bodypart" val="gloves" />
		<set name="immediate_effect" val="1" />
		<set name="crystal_count" val="139" />
		<set name="crystal_type" val="d" />
		<set name="material" val="fine_steel" />
		<set name="weight" val="620" />
		<set name="price" val="75200" />
		<set name="enchant_enabled" val="1" />
		<for>
			<add order="0x10" stat="pDef" val="29" />
			<enchant order="0x0C" stat="pDef" val="0" />
		</for>
	</item>
	<item id="608" type="Armor" name="미스릴 건틀렛">
		<set name="icon" val="icon.armor_t61_g_i00" />
		<set name="default_action" val="equip" />
		<set name="bodypart" val="gloves" />
		<set name="immediate_effect" val="1" />
		<set name="crystal_count" val="76" />
		<set name="crystal_type" val="c" />
		<set name="material" val="mithril" />
		<set name="weight" val="600" />
		<set name="price" val="188800" />
		<set name="enchant_enabled" val="1" />
		<for>
			<add order="0x10" stat="pDef" val="36" />
			<enchant order="0x0C" stat="pDef" val="0" />
		</for>
	</item>
	<item id="609" type="Armor" name="사령의 건틀렛">
		<set name="icon" val="icon.armor_gauntlet_i00" />
		<set name="default_action" val="equip" />
		<set name="bodypart" val="gloves" />
		<set name="immediate_effect" val="1" />
		<set name="crystal_count" val="143" />
		<set name="crystal_type" val="c" />
		<set name="material" val="blood_steel" />
		<set name="weight" val="1920" />
		<set name="price" val="275100" />
		<set name="enchant_enabled" val="1" />
		<for>
			<add order="0x10" stat="pDef" val="39" />
			<enchant order="0x0C" stat="pDef" val="0" />
		</for>
	</item>
	<item id="610" type="Armor" name="성기사의 건틀렛">
		<set name="icon" val="icon.armor_gauntlet_i00" />
		<set name="default_action" val="equip" />
		<set name="bodypart" val="gloves" />
		<set name="immediate_effect" val="1" />
		<set name="crystal_count" val="69" />
		<set name="crystal_type" val="b" />
		<set name="material" val="oriharukon" />
		<set name="weight" val="6400" />
		<set name="price" val="399100" />
		<set name="enchant_enabled" val="1" />
		<for>
			<add order="0x10" stat="pDef" val="41" />
			<enchant order="0x0C" stat="pDef" val="0" />
		</for>
	</item>
	<item id="611" type="Armor" name="흡령 건틀렛">
		<set name="icon" val="icon.armor_gauntlet_i00" />
		<set name="default_action" val="equip" />
		<set name="bodypart" val="gloves" />
		<set name="immediate_effect" val="1" />
		<set name="crystal_count" val="107" />
		<set name="crystal_type" val="b" />
		<set name="material" val="blood_steel" />
		<set name="weight" val="4800" />
		<set name="price" val="618800" />
		<set name="enchant_enabled" val="1" />
		<for>
			<add order="0x10" stat="pDef" val="44" />
			<enchant order="0x0C" stat="pDef" val="0" />
		</for>
	</item>
	<item id="612" type="Armor" name="봉인된 쉬르노엔의 건틀렛">
		<set name="icon" val="icon.armor_t64_g_i02" />
		<set name="default_action" val="equip" />
		<set name="bodypart" val="gloves" />
		<set name="immediate_effect" val="1" />
		<set name="crystal_count" val="53" />
		<set name="crystal_type" val="b" />
		<set name="material" val="mithril" />
		<set name="weight" val="590" />
		<set name="price" val="399100" />
		<set name="enchant_enabled" val="1" />
		<for>
			<add order="0x10" stat="pDef" val="41" />
			<enchant order="0x0C" stat="pDef" val="0" />
		</for>
	</item>
	<item id="613" type="Armor" name="사룡의 장갑">
		<set name="icon" val="icon.armor_gauntlet_i00" />
		<set name="default_action" val="equip" />
		<set name="bodypart" val="gloves" />
		<set name="immediate_effect" val="1" />
		<set name="crystal_count" val="140" />
		<set name="crystal_type" val="a" />
		<set name="material" val="damascus" />
		<set name="weight" val="3200" />
		<set name="price" val="1355000" />
		<set name="enchant_enabled" val="1" />
		<for>
			<add order="0x10" stat="pDef" val="48" />
			<enchant order="0x0C" stat="pDef" val="0" />
		</for>
	</item>
	<item id="614" type="Armor" name="기사의 망토">
		<set name="icon" val="icon.armor_back04" />
		<set name="default_action" val="equip" />
		<set name="bodypart" val="back" />
		<set name="immediate_effect" val="1" />
		<set name="crystal_count" val="38" />
		<set name="crystal_type" val="d" />
		<set name="material" val="cloth" />
		<set name="weight" val="240" />
		<set name="price" val="20900" />
		<set name="enchant_enabled" val="1" />
		<for>
			<add order="0x10" stat="pDef" val="7" />
			<enchant order="0x0C" stat="pDef" val="0" />
		</for>
	</item>
	<item id="615" type="Armor" name="거미줄 망토">
		<set name="icon" val="icon.armor_back05" />
		<set name="default_action" val="equip" />
		<set name="bodypart" val="back" />
		<set name="immediate_effect" val="1" />
		<set name="crystal_count" val="60" />
		<set name="crystal_type" val="d" />
		<set name="material" val="cobweb" />
		<set name="weight" val="240" />
		<set name="price" val="33300" />
		<set name="enchant_enabled" val="1" />
		<for>
			<add order="0x10" stat="pDef" val="8" />
			<enchant order="0x0C" stat="pDef" val="0" />
		</for>
	</item>
	<item id="616" type="Armor" name="마법의 망토">
		<set name="icon" val="icon.armor_back06" />
		<set name="default_action" val="equip" />
		<set name="bodypart" val="back" />
		<set name="immediate_effect" val="1" />
		<set name="crystal_count" val="135" />
		<set name="crystal_type" val="d" />
		<set name="material" val="cloth" />
		<set name="weight" val="240" />
		<set name="price" val="74700" />
		<set name="enchant_enabled" val="1" />
		<for>
			<add order="0x10" stat="pDef" val="11" />
			<enchant order="0x0C" stat="pDef" val="0" />
		</for>
	</item>
	<item id="617" type="Armor" name="미스릴 망토">
		<set name="icon" val="icon.armor_back07" />
		<set name="default_action" val="equip" />
		<set name="bodypart" val="back" />
		<set name="immediate_effect" val="1" />
		<set name="crystal_count" val="177" />
		<set name="crystal_type" val="d" />
		<set name="material" val="mithril" />
		<set name="weight" val="240" />
		<set name="price" val="97800" />
		<set name="enchant_enabled" val="1" />
		<for>
			<add order="0x10" stat="pDef" val="11" />
			<enchant order="0x0C" stat="pDef" val="0" />
		</for>
	</item>
	<item id="618" type="Armor" name="호신 망토">
		<set name="icon" val="icon.armor_back08" />
		<set name="default_action" val="equip" />
		<set name="bodypart" val="back" />
		<set name="immediate_effect" val="1" />
		<set name="crystal_count" val="64" />
		<set name="crystal_type" val="c" />
		<set name="material" val="cloth" />
		<set name="weight" val="240" />
		<set name="price" val="161000" />
		<set name="enchant_enabled" val="1" />
		<for>
			<add order="0x10" stat="pDef" val="13" />
			<enchant order="0x0C" stat="pDef" val="0" />
		</for>
	</item>
	<item id="619" type="Armor" name="(사용안함)고대의 망토">
		<set name="icon" val="icon.armor_back09" />
		<set name="default_action" val="equip" />
		<set name="bodypart" val="back" />
		<set name="immediate_effect" val="1" />
		<set name="crystal_count" val="98" />
		<set name="crystal_type" val="c" />
		<set name="material" val="cloth" />
		<set name="weight" val="230" />
		<set name="price" val="245000" />
		<set name="enchant_enabled" val="1" />
		<for>
			<add order="0x10" stat="pDef" val="15" />
			<enchant order="0x0C" stat="pDef" val="0" />
		</for>
	</item>
	<item id="620" type="Armor" name="수호의 망토">
		<set name="icon" val="icon.armor_back09" />
		<set name="default_action" val="equip" />
		<set name="bodypart" val="back" />
		<set name="immediate_effect" val="1" />
		<set name="crystal_count" val="143" />
		<set name="crystal_type" val="c" />
		<set name="material" val="cloth" />
		<set name="weight" val="230" />
		<set name="price" val="358000" />
		<set name="enchant_enabled" val="1" />
		<for>
			<add order="0x10" stat="pDef" val="16" />
			<enchant order="0x0C" stat="pDef" val="0" />
		</for>
	</item>
	<item id="621" type="Armor" name="지옥의 망토">
		<set name="icon" val="icon.armor_back09" />
		<set name="default_action" val="equip" />
		<set name="bodypart" val="back" />
		<set name="immediate_effect" val="1" />
		<set name="crystal_count" val="107" />
		<set name="crystal_type" val="b" />
		<set name="material" val="cloth" />
		<set name="weight" val="220" />
		<set name="price" val="804000" />
		<set name="enchant_enabled" val="1" />
		<for>
			<add order="0x10" stat="pDef" val="18" />
			<enchant order="0x0C" stat="pDef" val="0" />
		</for>
	</item>
	<item id="622" type="Armor" name="(사용안함)성령의 망토">
		<set name="icon" val="icon.armor_back09" />
		<set name="default_action" val="equip" />
		<set name="bodypart" val="back" />
		<set name="immediate_effect" val="1" />
		<set name="crystal_count" val="92" />
		<set name="crystal_type" val="a" />
		<set name="material" val="cloth" />
		<set name="weight" val="220" />
		<set name="price" val="1160000" />
		<set name="enchant_enabled" val="1" />
		<for>
			<add order="0x10" stat="pDef" val="18" />
			<enchant order="0x0C" stat="pDef" val="0" />
		</for>
	</item>
	<item id="623" type="Armor" name="신성의 망토">
		<set name="icon" val="icon.armor_back09" />
		<set name="default_action" val="equip" />
		<set name="bodypart" val="back" />
		<set name="immediate_effect" val="1" />
		<set name="crystal_count" val="140" />
		<set name="crystal_type" val="a" />
		<set name="material" val="cloth" />
		<set name="weight" val="220" />
		<set name="price" val="1760000" />
		<set name="enchant_enabled" val="1" />
		<for>
			<add order="0x10" stat="pDef" val="19" />
			<enchant order="0x0C" stat="pDef" val="0" />
		</for>
	</item>
	<item id="624" type="Armor" name="투명 망토">
		<set name="icon" val="icon.armor_back09" />
		<set name="default_action" val="equip" />
		<set name="bodypart" val="back" />
		<set name="immediate_effect" val="1" />
		<set name="material" val="cloth" />
		<set name="weight" val="260" />
		<set name="price" val="37" />
		<set name="is_dropable" val="false" />
		<for>
			<add order="0x10" stat="pDef" val="2" />
		</for>
	</item>
	<item id="625" type="Armor" name="골각 방패">
		<set name="icon" val="icon.shield_bone_shield_i00" />
		<set name="default_action" val="equip" />
		<set name="bodypart" val="lhand" />
		<set name="immediate_effect" val="1" />
		<set name="material" val="bone" />
		<set name="weight" val="1380" />
		<set name="price" val="9900" />
		<cond msgId="1518">
			<player races="Human,Elf,DarkElf,Orc,Dwarf" />
		</cond>
		<for>
			<sub order="0x10" stat="rEvas" val="8" />
			<set order="0x08" stat="rShld" val="20" />
			<set order="0x08" stat="sDef" val="90" />
			<enchant val="0" order="0x0C" stat="sDef" />
		</for>
	</item>
	<item id="626" type="Armor" name="청동 방패">
		<set name="icon" val="icon.shield_bronze_shield_i00" />
		<set name="default_action" val="equip" />
		<set name="bodypart" val="lhand" />
		<set name="immediate_effect" val="1" />
		<set name="crystal_count" val="31" />
		<set name="crystal_type" val="d" />
		<set name="material" val="bronze" />
		<set name="weight" val="1370" />
		<set name="price" val="16900" />
		<set name="enchant_enabled" val="1" />
		<cond msgId="1518">
			<player races="Human,Elf,DarkElf,Orc,Dwarf" />
		</cond>
		<for>
			<sub order="0x10" stat="rEvas" val="8" />
			<set order="0x08" stat="rShld" val="20" />
			<set order="0x08" stat="sDef" val="101" />
			<enchant val="0" order="0x0C" stat="sDef" />
		</for>
	</item>
	<item id="627" type="Armor" name="아스피스">
		<set name="icon" val="icon.shield_aspis_i00" />
		<set name="default_action" val="equip" />
		<set name="bodypart" val="lhand" />
		<set name="immediate_effect" val="1" />
		<set name="crystal_count" val="50" />
		<set name="crystal_type" val="d" />
		<set name="material" val="steel" />
		<set name="weight" val="1350" />
		<set name="price" val="26900" />
		<set name="enchant_enabled" val="1" />
		<cond msgId="1518">
			<player races="Human,Elf,DarkElf,Orc,Dwarf" />
		</cond>
		<for>
			<sub order="0x10" stat="rEvas" val="8" />
			<set order="0x08" stat="rShld" val="20" />
			<set order="0x08" stat="sDef" val="114" />
			<enchant val="0" order="0x0C" stat="sDef" />
		</for>
	</item>
	<item id="628" type="Armor" name="호플론">
		<set name="icon" val="icon.shield_hoplon_i00" />
		<set name="default_action" val="equip" />
		<set name="bodypart" val="lhand" />
		<set name="immediate_effect" val="1" />
		<set name="crystal_count" val="76" />
		<set name="crystal_type" val="d" />
		<set name="material" val="fine_steel" />
		<set name="weight" val="1340" />
		<set name="price" val="41000" />
		<set name="enchant_enabled" val="1" />
		<cond msgId="1518">
			<player races="Human,Elf,DarkElf,Orc,Dwarf" />
		</cond>
		<for>
			<sub order="0x10" stat="rEvas" val="8" />
			<set order="0x08" stat="rShld" val="20" />
			<set order="0x08" stat="sDef" val="128" />
			<enchant val="0" order="0x0C" stat="sDef" />
		</for>
	</item>
	<item id="629" type="Armor" name="카이트쉴드">
		<set name="icon" val="icon.shield_kite_shield_i00" />
		<set name="default_action" val="equip" />
		<set name="bodypart" val="lhand" />
		<set name="immediate_effect" val="1" />
		<set name="crystal_count" val="111" />
		<set name="crystal_type" val="d" />
		<set name="material" val="fine_steel" />
		<set name="weight" val="1320" />
		<set name="price" val="60300" />
		<set name="enchant_enabled" val="1" />
		<cond msgId="1518">
			<player races="Human,Elf,DarkElf,Orc,Dwarf" />
		</cond>
		<for>
			<sub order="0x10" stat="rEvas" val="8" />
			<set order="0x08" stat="rShld" val="20" />
			<set order="0x08" stat="sDef" val="142" />
			<enchant val="0" order="0x0C" stat="sDef" />
		</for>
	</item>
	<item id="630" type="Armor" name="사각 방패">
		<set name="icon" val="icon.shield_square_shield_i00" />
		<set name="default_action" val="equip" />
		<set name="bodypart" val="lhand" />
		<set name="immediate_effect" val="1" />
		<set name="crystal_count" val="146" />
		<set name="crystal_type" val="d" />
		<set name="material" val="fine_steel" />
		<set name="weight" val="1310" />
		<set name="price" val="79000" />
		<set name="enchant_enabled" val="1" />
		<cond msgId="1518">
			<player races="Human,Elf,DarkElf,Orc,Dwarf" />
		</cond>
		<for>
			<sub order="0x10" stat="rEvas" val="8" />
			<set order="0x08" stat="rShld" val="20" />
			<set order="0x08" stat="sDef" val="154" />
			<enchant val="0" order="0x0C" stat="sDef" />
		</for>
	</item>
	<item id="631" type="Armor" name="엘다라크">
		<set name="icon" val="icon.shield_eldarake_i00" />
		<set name="default_action" val="equip" />
		<set name="bodypart" val="lhand" />
		<set name="immediate_effect" val="1" />
		<set name="crystal_count" val="41" />
		<set name="crystal_type" val="c" />
		<set name="material" val="fine_steel" />
		<set name="weight" val="1290" />
		<set name="price" val="102000" />
		<set name="enchant_enabled" val="1" />
		<cond msgId="1518">
			<player races="Human,Elf,DarkElf,Orc,Dwarf" />
		</cond>
		<for>
			<sub order="0x10" stat="rEvas" val="8" />
			<set order="0x08" stat="rShld" val="20" />
			<set order="0x08" stat="sDef" val="166" />
			<enchant val="0" order="0x0C" stat="sDef" />
		</for>
	</item>
	<item id="632" type="Armor" name="나이트 쉴드">
		<set name="icon" val="icon.shield_knight_shield_i00" />
		<set name="default_action" val="equip" />
		<set name="bodypart" val="lhand" />
		<set name="immediate_effect" val="1" />
		<set name="crystal_count" val="52" />
		<set name="crystal_type" val="c" />
		<set name="material" val="fine_steel" />
		<set name="weight" val="1260" />
		<set name="price" val="130100" />
		<set name="enchant_enabled" val="1" />
		<cond msgId="1518">
			<player races="Human,Elf,DarkElf,Orc,Dwarf" />
		</cond>
		<for>
			<sub order="0x10" stat="rEvas" val="8" />
			<set order="0x08" stat="rShld" val="20" />
			<set order="0x08" stat="sDef" val="178" />
			<enchant val="0" order="0x0C" stat="sDef" />
		</for>
	</item>
	<item id="633" type="Armor" name="쉬르노엔의 쉴드">
		<set name="icon" val="icon.shield_shrnoens_shield_i00" />
		<set name="default_action" val="equip" />
		<set name="bodypart" val="lhand" />
		<set name="immediate_effect" val="1" />
		<set name="crystal_count" val="56" />
		<set name="crystal_type" val="b" />
		<set name="material" val="mithril" />
		<set name="weight" val="1210" />
		<set name="price" val="419000" />
		<set name="enchant_enabled" val="1" />
		<cond msgId="1518">
			<player races="Human,Elf,DarkElf,Orc,Dwarf" />
		</cond>
		<for>
			<sub order="0x10" stat="rEvas" val="8" />
			<set order="0x08" stat="rShld" val="20" />
			<set order="0x08" stat="sDef" val="216" />
			<enchant val="0" order="0x0C" stat="sDef" />
		</for>
	</item>
	<item id="634" type="Armor" name="드래곤 카이트">
		<set name="icon" val="icon.shield_shield_of_nightmare_i00" />
		<set name="default_action" val="equip" />
		<set name="bodypart" val="lhand" />
		<set name="immediate_effect" val="1" />
		<set name="crystal_count" val="125" />
		<set name="crystal_type" val="s" />
		<set name="material" val="bone" />
		<set name="weight" val="1170" />
		<set name="price" val="1949000" />
		<set name="enchant_enabled" val="1" />
		<set name="is_dropable" val="false" />
		<cond msgId="1518">
			<player races="Human,Elf,DarkElf,Orc,Dwarf" />
		</cond>
		<for>
			<sub order="0x10" stat="rEvas" val="8" />
			<set order="0x08" stat="rShld" val="20" />
			<set order="0x08" stat="sDef" val="269" />
			<enchant val="0" order="0x0C" stat="sDef" />
		</for>
	</item>
	<item id="635" type="Armor" name="늑대의 방패">
		<set name="icon" val="icon.shield_small_shield_i00" />
		<set name="default_action" val="equip" />
		<set name="bodypart" val="lhand" />
		<set name="immediate_effect" val="1" />
		<set name="crystal_count" val="72" />
		<set name="crystal_type" val="b" />
		<set name="material" val="oriharukon" />
		<set name="weight" val="640" />
		<set name="price" val="419000" />
		<set name="enchant_enabled" val="1" />
		<cond msgId="1518">
			<player races="Human,Elf,DarkElf,Orc,Dwarf" />
		</cond>
		<for>
			<sub order="0x10" stat="rEvas" val="8" />
			<set order="0x08" stat="rShld" val="20" />
			<set order="0x08" stat="sDef" val="216" />
			<enchant val="0" order="0x0C" stat="sDef" />
		</for>
	</item>
	<item id="636" type="Armor" name="광룡의 방패">
		<set name="icon" val="icon.shield_doom_shield_i00" />
		<set name="default_action" val="equip" />
		<set name="bodypart" val="lhand" />
		<set name="immediate_effect" val="1" />
		<set name="crystal_count" val="112" />
		<set name="crystal_type" val="b" />
		<set name="material" val="mithril" />
		<set name="weight" val="720" />
		<set name="price" val="649800" />
		<set name="enchant_enabled" val="1" />
		<cond msgId="1518">
			<player races="Human,Elf,DarkElf,Orc,Dwarf" />
		</cond>
		<for>
			<sub order="0x10" stat="rEvas" val="8" />
			<set order="0x08" stat="rShld" val="20" />
			<set order="0x08" stat="sDef" val="230" />
			<enchant val="0" order="0x0C" stat="sDef" />
		</for>
	</item>
	<item id="637" type="Armor" name="무용의 방패">
		<set name="icon" val="icon.shield_small_shield_i00" />
		<set name="default_action" val="equip" />
		<set name="bodypart" val="lhand" />
		<set name="immediate_effect" val="1" />
		<set name="crystal_count" val="112" />
		<set name="crystal_type" val="b" />
		<set name="material" val="blood_steel" />
		<set name="weight" val="720" />
		<set name="price" val="649800" />
		<set name="enchant_enabled" val="1" />
		<cond msgId="1518">
			<player races="Human,Elf,DarkElf,Orc,Dwarf" />
		</cond>
		<for>
			<sub order="0x10" stat="rEvas" val="8" />
			<set order="0x08" stat="rShld" val="20" />
			<set order="0x08" stat="sDef" val="230" />
			<enchant val="0" order="0x0C" stat="sDef" />
		</for>
	</item>
	<item id="638" type="Armor" name="명예의 방패">
		<set name="icon" val="icon.shield_shield_of_victory_i00" />
		<set name="default_action" val="equip" />
		<set name="bodypart" val="lhand" />
		<set name="immediate_effect" val="1" />
		<set name="crystal_count" val="72" />
		<set name="crystal_type" val="b" />
		<set name="material" val="fine_steel" />
		<set name="weight" val="800" />
		<set name="price" val="419000" />
		<set name="enchant_enabled" val="1" />
		<cond msgId="1518">
			<player races="Human,Elf,DarkElf,Orc,Dwarf" />
		</cond>
		<for>
			<sub order="0x10" stat="rEvas" val="8" />
			<set order="0x08" stat="rShld" val="20" />
			<set order="0x08" stat="sDef" val="216" />
			<enchant val="0" order="0x0C" stat="sDef" />
		</for>
	</item>
	<item id="639" type="Armor" name="홍염의 방패">
		<set name="icon" val="icon.shield_tower_shield_i00" />
		<set name="default_action" val="equip" />
		<set name="bodypart" val="lhand" />
		<set name="immediate_effect" val="1" />
		<set name="crystal_count" val="112" />
		<set name="crystal_type" val="b" />
		<set name="material" val="blood_steel" />
		<set name="weight" val="960" />
		<set name="price" val="649800" />
		<set name="enchant_enabled" val="1" />
		<cond msgId="1518">
			<player races="Human,Elf,DarkElf,Orc,Dwarf" />
		</cond>
		<for>
			<sub order="0x10" stat="rEvas" val="8" />
			<set order="0x08" stat="rShld" val="20" />
			<set order="0x08" stat="sDef" val="230" />
			<enchant val="0" order="0x0C" stat="sDef" />
		</for>
	</item>
	<item id="640" type="Armor" name="엘븐 크리스탈 쉴드">
		<set name="icon" val="icon.shield_masterpiece_shield_i00" />
		<set name="default_action" val="equip" />
		<set name="bodypart" val="lhand" />
		<set name="immediate_effect" val="1" />
		<set name="crystal_count" val="72" />
		<set name="crystal_type" val="b" />
		<set name="material" val="crystal" />
		<set name="weight" val="720" />
		<set name="price" val="419000" />
		<set name="enchant_enabled" val="1" />
		<cond msgId="1518">
			<player races="Human,Elf,DarkElf,Orc,Dwarf" />
		</cond>
		<for>
			<sub order="0x10" stat="rEvas" val="8" />
			<set order="0x08" stat="rShld" val="20" />
			<set order="0x08" stat="sDef" val="216" />
			<enchant val="0" order="0x0C" stat="sDef" />
		</for>
	</item>
	<item id="641" type="Armor" name="다크 크리스탈 쉴드">
		<set name="icon" val="icon.shield_dark_crystal_shield_i00" />
		<set name="default_action" val="equip" />
		<set name="bodypart" val="lhand" />
		<set name="immediate_effect" val="1" />
		<set name="crystal_count" val="75" />
		<set name="crystal_type" val="a" />
		<set name="material" val="crystal" />
		<set name="weight" val="1190" />
		<set name="price" val="935000" />
		<set name="enchant_enabled" val="1" />
		<cond msgId="1518">
			<player races="Human,Elf,DarkElf,Orc,Dwarf" />
		</cond>
		<for>
			<sub order="0x10" stat="rEvas" val="8" />
			<set order="0x08" stat="rShld" val="20" />
			<set order="0x08" stat="sDef" val="243" />
			<enchant val="0" order="0x0C" stat="sDef" />
		</for>
	</item>
	<item id="642" type="Armor" name="엘븐배지언쉴드">
		<set name="icon" val="icon.shield_shield_of_victory_i00" />
		<set name="default_action" val="equip" />
		<set name="bodypart" val="lhand" />
		<set name="immediate_effect" val="1" />
		<set name="crystal_count" val="72" />
		<set name="crystal_type" val="b" />
		<set name="material" val="mithril" />
		<set name="weight" val="560" />
		<set name="price" val="419000" />
		<set name="enchant_enabled" val="1" />
		<cond msgId="1518">
			<player races="Human,Elf,DarkElf,Orc,Dwarf" />
		</cond>
		<for>
			<sub order="0x10" stat="rEvas" val="8" />
			<set order="0x08" stat="rShld" val="20" />
			<set order="0x08" stat="sDef" val="216" />
			<enchant val="0" order="0x0C" stat="sDef" />
		</for>
	</item>
	<item id="643" type="Armor" name="다크배지언쉴드">
		<set name="icon" val="icon.shield_shield_of_victory_i00" />
		<set name="default_action" val="equip" />
		<set name="bodypart" val="lhand" />
		<set name="immediate_effect" val="1" />
		<set name="crystal_count" val="112" />
		<set name="crystal_type" val="b" />
		<set name="material" val="mithril" />
		<set name="weight" val="560" />
		<set name="price" val="649800" />
		<set name="enchant_enabled" val="1" />
		<cond msgId="1518">
			<player races="Human,Elf,DarkElf,Orc,Dwarf" />
		</cond>
		<for>
			<sub order="0x10" stat="rEvas" val="8" />
			<set order="0x08" stat="rShld" val="20" />
			<set order="0x08" stat="sDef" val="230" />
			<enchant val="0" order="0x0C" stat="sDef" />
		</for>
	</item>
	<item id="644" type="Armor" name="헬 쉴드">
		<set name="icon" val="icon.shield_shield_of_grace_i00" />
		<set name="default_action" val="equip" />
		<set name="bodypart" val="lhand" />
		<set name="immediate_effect" val="1" />
		<set name="crystal_count" val="112" />
		<set name="crystal_type" val="b" />
		<set name="material" val="blood_steel" />
		<set name="weight" val="640" />
		<set name="price" val="649800" />
		<set name="enchant_enabled" val="1" />
		<cond msgId="1518">
			<player races="Human,Elf,DarkElf,Orc,Dwarf" />
		</cond>
		<for>
			<sub order="0x10" stat="rEvas" val="8" />
			<set order="0x08" stat="rShld" val="20" />
			<set order="0x08" stat="sDef" val="230" />
			<enchant val="0" order="0x0C" stat="sDef" />
		</for>
	</item>
	<item id="645" type="Armor" name="아트 오브 쉴드">
		<set name="icon" val="icon.shield_knight_shield_i00" />
		<set name="default_action" val="equip" />
		<set name="bodypart" val="lhand" />
		<set name="immediate_effect" val="1" />
		<set name="crystal_count" val="72" />
		<set name="crystal_type" val="b" />
		<set name="material" val="chrysolite" />
		<set name="weight" val="560" />
		<set name="price" val="419000" />
		<set name="enchant_enabled" val="1" />
		<cond msgId="1518">
			<player races="Human,Elf,DarkElf,Orc,Dwarf" />
		</cond>
		<for>
			<sub order="0x10" stat="rEvas" val="8" />
			<set order="0x08" stat="rShld" val="20" />
			<set order="0x08" stat="sDef" val="216" />
			<enchant val="0" order="0x0C" stat="sDef" />
		</for>
	</item>
	<item id="646" type="Armor" name="침묵의 방패">
		<set name="icon" val="icon.shield_shield_of_assistance_i00" />
		<set name="default_action" val="equip" />
		<set name="bodypart" val="lhand" />
		<set name="immediate_effect" val="1" />
		<set name="crystal_count" val="72" />
		<set name="crystal_type" val="b" />
		<set name="material" val="damascus" />
		<set name="weight" val="640" />
		<set name="price" val="419000" />
		<set name="enchant_enabled" val="1" />
		<cond msgId="1518">
			<player races="Human,Elf,DarkElf,Orc,Dwarf" />
		</cond>
		<for>
			<sub order="0x10" stat="rEvas" val="8" />
			<set order="0x08" stat="rShld" val="20" />
			<set order="0x08" stat="sDef" val="216" />
			<enchant val="0" order="0x0C" stat="sDef" />
		</for>
	</item>
	<item id="647" type="Armor" name="질풍의 방패">
		<set name="icon" val="icon.shield_shield_of_grace_i00" />
		<set name="default_action" val="equip" />
		<set name="bodypart" val="lhand" />
		<set name="immediate_effect" val="1" />
		<set name="crystal_count" val="112" />
		<set name="crystal_type" val="b" />
		<set name="material" val="blood_steel" />
		<set name="weight" val="720" />
		<set name="price" val="649800" />
		<set name="enchant_enabled" val="1" />
		<cond msgId="1518">
			<player races="Human,Elf,DarkElf,Orc,Dwarf" />
		</cond>
		<for>
			<sub order="0x10" stat="rEvas" val="8" />
			<set order="0x08" stat="rShld" val="20" />
			<set order="0x08" stat="sDef" val="230" />
			<enchant val="0" order="0x0C" stat="sDef" />
		</for>
	</item>
	<item id="648" type="Armor" name="프레어리 쉴드">
		<set name="icon" val="icon.shield_knight_shield_i00" />
		<set name="default_action" val="equip" />
		<set name="bodypart" val="lhand" />
		<set name="immediate_effect" val="1" />
		<set name="crystal_count" val="72" />
		<set name="crystal_type" val="b" />
		<set name="material" val="chrysolite" />
		<set name="weight" val="800" />
		<set name="price" val="419000" />
		<set name="enchant_enabled" val="1" />
		<cond msgId="1518">
			<player races="Human,Elf,DarkElf,Orc,Dwarf" />
		</cond>
		<for>
			<sub order="0x10" stat="rEvas" val="8" />
			<set order="0x08" stat="rShld" val="20" />
			<set order="0x08" stat="sDef" val="216" />
			<enchant val="0" order="0x0C" stat="sDef" />
		</for>
	</item>
	<item id="649" type="Armor" name="쉴드 오브 언더월드">
		<set name="icon" val="icon.shield_knight_shield_i00" />
		<set name="default_action" val="equip" />
		<set name="bodypart" val="lhand" />
		<set name="immediate_effect" val="1" />
		<set name="crystal_count" val="112" />
		<set name="crystal_type" val="b" />
		<set name="material" val="damascus" />
		<set name="weight" val="880" />
		<set name="price" val="649800" />
		<set name="enchant_enabled" val="1" />
		<cond msgId="1518">
			<player races="Human,Elf,DarkElf,Orc,Dwarf" />
		</cond>
		<for>
			<sub order="0x10" stat="rEvas" val="8" />
			<set order="0x08" stat="rShld" val="20" />
			<set order="0x08" stat="sDef" val="230" />
			<enchant val="0" order="0x0C" stat="sDef" />
		</for>
	</item>
	<item id="650" type="Armor" name="집중의 방패">
		<set name="icon" val="icon.shield_shield_of_grace_i00" />
		<set name="default_action" val="equip" />
		<set name="bodypart" val="lhand" />
		<set name="immediate_effect" val="1" />
		<set name="crystal_count" val="72" />
		<set name="crystal_type" val="b" />
		<set name="material" val="oriharukon" />
		<set name="weight" val="960" />
		<set name="price" val="419000" />
		<set name="enchant_enabled" val="1" />
		<cond msgId="1518">
			<player races="Human,Elf,DarkElf,Orc,Dwarf" />
		</cond>
		<for>
			<sub order="0x10" stat="rEvas" val="8" />
			<set order="0x08" stat="rShld" val="20" />
			<set order="0x08" stat="sDef" val="216" />
			<enchant val="0" order="0x0C" stat="sDef" />
		</for>
	</item>
	<item id="651" type="Armor" name="신궁의 방패">
		<set name="icon" val="icon.shield_shield_of_assistance_i00" />
		<set name="default_action" val="equip" />
		<set name="bodypart" val="lhand" />
		<set name="immediate_effect" val="1" />
		<set name="crystal_count" val="112" />
		<set name="crystal_type" val="b" />
		<set name="material" val="oriharukon" />
		<set name="weight" val="1040" />
		<set name="price" val="649800" />
		<set name="enchant_enabled" val="1" />
		<cond msgId="1518">
			<player races="Human,Elf,DarkElf,Orc,Dwarf" />
		</cond>
		<for>
			<sub order="0x10" stat="rEvas" val="8" />
			<set order="0x08" stat="rShld" val="20" />
			<set order="0x08" stat="sDef" val="230" />
			<enchant val="0" order="0x0C" stat="sDef" />
		</for>
	</item>
	<item id="652" type="Armor" name="가디언스 쉴드">
		<set name="icon" val="icon.shield_knight_shield_i00" />
		<set name="default_action" val="equip" />
		<set name="bodypart" val="lhand" />
		<set name="immediate_effect" val="1" />
		<set name="crystal_count" val="72" />
		<set name="crystal_type" val="b" />
		<set name="material" val="mithril" />
		<set name="weight" val="1120" />
		<set name="price" val="419000" />
		<set name="enchant_enabled" val="1" />
		<cond msgId="1518">
			<player races="Human,Elf,DarkElf,Orc,Dwarf" />
		</cond>
		<for>
			<sub order="0x10" stat="rEvas" val="8" />
			<set order="0x08" stat="rShld" val="20" />
			<set order="0x08" stat="sDef" val="216" />
			<enchant val="0" order="0x0C" stat="sDef" />
		</for>
	</item>
	<item id="653" type="Armor" name="스나이퍼 쉴드">
		<set name="icon" val="icon.shield_doom_shield_i00" />
		<set name="default_action" val="equip" />
		<set name="bodypart" val="lhand" />
		<set name="immediate_effect" val="1" />
		<set name="crystal_count" val="112" />
		<set name="crystal_type" val="b" />
		<set name="material" val="leather" />
		<set name="weight" val="1200" />
		<set name="price" val="649800" />
		<set name="enchant_enabled" val="1" />
		<cond msgId="1518">
			<player races="Human,Elf,DarkElf,Orc,Dwarf" />
		</cond>
		<for>
			<sub order="0x10" stat="rEvas" val="8" />
			<set order="0x08" stat="rShld" val="20" />
			<set order="0x08" stat="sDef" val="230" />
			<enchant val="0" order="0x0C" stat="sDef" />
		</for>
	</item>
	<item id="654" type="Armor" name="마나의 방패">
		<set name="icon" val="icon.shield_shield_of_pledge_i00" />
		<set name="default_action" val="equip" />
		<set name="bodypart" val="lhand" />
		<set name="immediate_effect" val="1" />
		<set name="crystal_count" val="72" />
		<set name="crystal_type" val="b" />
		<set name="material" val="mithril" />
		<set name="weight" val="480" />
		<set name="price" val="419000" />
		<set name="enchant_enabled" val="1" />
		<cond msgId="1518">
			<player races="Human,Elf,DarkElf,Orc,Dwarf" />
		</cond>
		<for>
			<sub order="0x10" stat="rEvas" val="8" />
			<set order="0x08" stat="rShld" val="20" />
			<set order="0x08" stat="sDef" val="216" />
			<enchant val="0" order="0x0C" stat="sDef" />
		</for>
	</item>
	<item id="655" type="Armor" name="현자의 방패">
		<set name="icon" val="icon.shield_sages_shield_i00" />
		<set name="default_action" val="equip" />
		<set name="bodypart" val="lhand" />
		<set name="immediate_effect" val="1" />
		<set name="crystal_count" val="112" />
		<set name="crystal_type" val="b" />
		<set name="material" val="steel" />
		<set name="weight" val="560" />
		<set name="price" val="649800" />
		<set name="enchant_enabled" val="1" />
		<cond msgId="1518">
			<player races="Human,Elf,DarkElf,Orc,Dwarf" />
		</cond>
		<for>
			<sub order="0x10" stat="rEvas" val="8" />
			<set order="0x08" stat="rShld" val="20" />
			<set order="0x08" stat="sDef" val="230" />
			<enchant val="0" order="0x0C" stat="sDef" />
		</for>
	</item>
	<item id="656" type="Armor" name="패러디아 쉴드">
		<set name="icon" val="icon.shield_knight_shield_i00" />
		<set name="default_action" val="equip" />
		<set name="bodypart" val="lhand" />
		<set name="immediate_effect" val="1" />
		<set name="crystal_count" val="72" />
		<set name="crystal_type" val="b" />
		<set name="material" val="chrysolite" />
		<set name="weight" val="480" />
		<set name="price" val="419000" />
		<set name="enchant_enabled" val="1" />
		<cond msgId="1518">
			<player races="Human,Elf,DarkElf,Orc,Dwarf" />
		</cond>
		<for>
			<sub order="0x10" stat="rEvas" val="8" />
			<set order="0x08" stat="rShld" val="20" />
			<set order="0x08" stat="sDef" val="216" />
			<enchant val="0" order="0x0C" stat="sDef" />
		</for>
	</item>
	<item id="657" type="Armor" name="인페르노 쉴드">
		<set name="icon" val="icon.shield_shield_of_victory_i00" />
		<set name="default_action" val="equip" />
		<set name="bodypart" val="lhand" />
		<set name="immediate_effect" val="1" />
		<set name="crystal_count" val="112" />
		<set name="crystal_type" val="b" />
		<set name="material" val="blood_steel" />
		<set name="weight" val="560" />
		<set name="price" val="649800" />
		<set name="enchant_enabled" val="1" />
		<cond msgId="1518">
			<player races="Human,Elf,DarkElf,Orc,Dwarf" />
		</cond>
		<for>
			<sub order="0x10" stat="rEvas" val="8" />
			<set order="0x08" stat="rShld" val="20" />
			<set order="0x08" stat="sDef" val="230" />
			<enchant val="0" order="0x0C" stat="sDef" />
		</for>
	</item>
	<item id="658" type="Armor" name="흑광의 방패">
		<set name="icon" val="icon.shield_composite_shield_i00" />
		<set name="default_action" val="equip" />
		<set name="bodypart" val="lhand" />
		<set name="immediate_effect" val="1" />
		<set name="crystal_count" val="112" />
		<set name="crystal_type" val="b" />
		<set name="material" val="damascus" />
		<set name="weight" val="560" />
		<set name="price" val="649800" />
		<set name="enchant_enabled" val="1" />
		<cond msgId="1518">
			<player races="Human,Elf,DarkElf,Orc,Dwarf" />
		</cond>
		<for>
			<sub order="0x10" stat="rEvas" val="8" />
			<set order="0x08" stat="rShld" val="20" />
			<set order="0x08" stat="sDef" val="230" />
			<enchant val="0" order="0x0C" stat="sDef" />
		</for>
	</item>
	<item id="659" type="Armor" name="소환의 방패">
		<set name="icon" val="icon.shield_shield_of_sola_eclipse_i00" />
		<set name="default_action" val="equip" />
		<set name="bodypart" val="lhand" />
		<set name="immediate_effect" val="1" />
		<set name="crystal_count" val="72" />
		<set name="crystal_type" val="b" />
		<set name="material" val="leather" />
		<set name="weight" val="480" />
		<set name="price" val="419000" />
		<set name="enchant_enabled" val="1" />
		<cond msgId="1518">
			<player races="Human,Elf,DarkElf,Orc,Dwarf" />
		</cond>
		<for>
			<sub order="0x10" stat="rEvas" val="8" />
			<set order="0x08" stat="rShld" val="20" />
			<set order="0x08" stat="sDef" val="216" />
			<enchant val="0" order="0x0C" stat="sDef" />
		</for>
	</item>
	<item id="660" type="Armor" name="이계의 방패">
		<set name="icon" val="icon.shield_round_shield_i00" />
		<set name="default_action" val="equip" />
		<set name="bodypart" val="lhand" />
		<set name="immediate_effect" val="1" />
		<set name="crystal_count" val="112" />
		<set name="crystal_type" val="b" />
		<set name="material" val="adamantaite" />
		<set name="weight" val="560" />
		<set name="price" val="649800" />
		<set name="enchant_enabled" val="1" />
		<cond msgId="1518">
			<player races="Human,Elf,DarkElf,Orc,Dwarf" />
		</cond>
		<for>
			<sub order="0x10" stat="rEvas" val="8" />
			<set order="0x08" stat="rShld" val="20" />
			<set order="0x08" stat="sDef" val="230" />
			<enchant val="0" order="0x0C" stat="sDef" />
		</for>
	</item>
	<item id="661" type="Armor" name="엘레멘탈 쉴드">
		<set name="icon" val="icon.shield_knight_shield_i00" />
		<set name="default_action" val="equip" />
		<set name="bodypart" val="lhand" />
		<set name="immediate_effect" val="1" />
		<set name="crystal_count" val="72" />
		<set name="crystal_type" val="b" />
		<set name="material" val="mithril" />
		<set name="weight" val="480" />
		<set name="price" val="419000" />
		<set name="enchant_enabled" val="1" />
		<cond msgId="1518">
			<player races="Human,Elf,DarkElf,Orc,Dwarf" />
		</cond>
		<for>
			<sub order="0x10" stat="rEvas" val="8" />
			<set order="0x08" stat="rShld" val="20" />
			<set order="0x08" stat="sDef" val="216" />
			<enchant val="0" order="0x0C" stat="sDef" />
		</for>
	</item>
	<item id="662" type="Armor" name="쉴드 오브 팬텀">
		<set name="icon" val="icon.shield_shield_of_assistance_i00" />
		<set name="default_action" val="equip" />
		<set name="bodypart" val="lhand" />
		<set name="immediate_effect" val="1" />
		<set name="crystal_count" val="112" />
		<set name="crystal_type" val="b" />
		<set name="material" val="oriharukon" />
		<set name="weight" val="560" />
		<set name="price" val="649800" />
		<set name="enchant_enabled" val="1" />
		<cond msgId="1518">
			<player races="Human,Elf,DarkElf,Orc,Dwarf" />
		</cond>
		<for>
			<sub order="0x10" stat="rEvas" val="8" />
			<set order="0x08" stat="rShld" val="20" />
			<set order="0x08" stat="sDef" val="230" />
			<enchant val="0" order="0x0C" stat="sDef" />
		</for>
	</item>
	<item id="663" type="Armor" name="은총의 방패">
		<set name="icon" val="icon.shield_leather_shield_i00" />
		<set name="default_action" val="equip" />
		<set name="bodypart" val="lhand" />
		<set name="immediate_effect" val="1" />
		<set name="crystal_count" val="72" />
		<set name="crystal_type" val="b" />
		<set name="material" val="mithril" />
		<set name="weight" val="480" />
		<set name="price" val="419000" />
		<set name="enchant_enabled" val="1" />
		<cond msgId="1518">
			<player races="Human,Elf,DarkElf,Orc,Dwarf" />
		</cond>
		<for>
			<sub order="0x10" stat="rEvas" val="8" />
			<set order="0x08" stat="rShld" val="20" />
			<set order="0x08" stat="sDef" val="216" />
			<enchant val="0" order="0x0C" stat="sDef" />
		</for>
	</item>
	<item id="664" type="Armor" name="성령의 방패">
		<set name="icon" val="icon.shield_composite_shield_i00" />
		<set name="default_action" val="equip" />
		<set name="bodypart" val="lhand" />
		<set name="immediate_effect" val="1" />
		<set name="crystal_count" val="112" />
		<set name="crystal_type" val="b" />
		<set name="material" val="chrysolite" />
		<set name="weight" val="560" />
		<set name="price" val="649800" />
		<set name="enchant_enabled" val="1" />
		<cond msgId="1518">
			<player races="Human,Elf,DarkElf,Orc,Dwarf" />
		</cond>
		<for>
			<sub order="0x10" stat="rEvas" val="8" />
			<set order="0x08" stat="rShld" val="20" />
			<set order="0x08" stat="sDef" val="230" />
			<enchant val="0" order="0x0C" stat="sDef" />
		</for>
	</item>
	<item id="665" type="Armor" name="피닉스 쉴드">
		<set name="icon" val="icon.shield_knight_shield_i00" />
		<set name="default_action" val="equip" />
		<set name="bodypart" val="lhand" />
		<set name="immediate_effect" val="1" />
		<set name="crystal_count" val="72" />
		<set name="crystal_type" val="b" />
		<set name="material" val="blood_steel" />
		<set name="weight" val="480" />
		<set name="price" val="419000" />
		<set name="enchant_enabled" val="1" />
		<cond msgId="1518">
			<player races="Human,Elf,DarkElf,Orc,Dwarf" />
		</cond>
		<for>
			<sub order="0x10" stat="rEvas" val="8" />
			<set order="0x08" stat="rShld" val="20" />
			<set order="0x08" stat="sDef" val="216" />
			<enchant val="0" order="0x0C" stat="sDef" />
		</for>
	</item>
	<item id="666" type="Armor" name="켈베로스 쉴드">
		<set name="icon" val="icon.shield_doom_shield_i00" />
		<set name="default_action" val="equip" />
		<set name="bodypart" val="lhand" />
		<set name="immediate_effect" val="1" />
		<set name="crystal_count" val="112" />
		<set name="crystal_type" val="b" />
		<set name="material" val="damascus" />
		<set name="weight" val="560" />
		<set name="price" val="649800" />
		<set name="enchant_enabled" val="1" />
		<cond msgId="1518">
			<player races="Human,Elf,DarkElf,Orc,Dwarf" />
		</cond>
		<for>
			<sub order="0x10" stat="rEvas" val="8" />
			<set order="0x08" stat="rShld" val="20" />
			<set order="0x08" stat="sDef" val="230" />
			<enchant val="0" order="0x0C" stat="sDef" />
		</for>
	</item>
	<item id="667" type="Armor" name="조력의 방패">
		<set name="icon" val="icon.shield_shield_of_assistance_i00" />
		<set name="default_action" val="equip" />
		<set name="bodypart" val="lhand" />
		<set name="immediate_effect" val="1" />
		<set name="crystal_count" val="72" />
		<set name="crystal_type" val="b" />
		<set name="material" val="fine_steel" />
		<set name="weight" val="480" />
		<set name="price" val="419000" />
		<set name="enchant_enabled" val="1" />
		<cond msgId="1518">
			<player races="Human,Elf,DarkElf,Orc,Dwarf" />
		</cond>
		<for>
			<sub order="0x10" stat="rEvas" val="8" />
			<set order="0x08" stat="rShld" val="20" />
			<set order="0x08" stat="sDef" val="216" />
			<enchant val="0" order="0x0C" stat="sDef" />
		</for>
	</item>
	<item id="668" type="Armor" name="축복의 방패">
		<set name="icon" val="icon.shield_shield_of_pledge_i00" />
		<set name="default_action" val="equip" />
		<set name="bodypart" val="lhand" />
		<set name="immediate_effect" val="1" />
		<set name="crystal_count" val="112" />
		<set name="crystal_type" val="b" />
		<set name="material" val="adamantaite" />
		<set name="weight" val="560" />
		<set name="price" val="649800" />
		<set name="enchant_enabled" val="1" />
		<cond msgId="1518">
			<player races="Human,Elf,DarkElf,Orc,Dwarf" />
		</cond>
		<for>
			<sub order="0x10" stat="rEvas" val="8" />
			<set order="0x08" stat="rShld" val="20" />
			<set order="0x08" stat="sDef" val="230" />
			<enchant val="0" order="0x0C" stat="sDef" />
		</for>
	</item>
	<item id="669" type="Armor" name="프레임 쉴드">
		<set name="icon" val="icon.shield_composite_shield_i00" />
		<set name="default_action" val="equip" />
		<set name="bodypart" val="lhand" />
		<set name="immediate_effect" val="1" />
		<set name="crystal_count" val="72" />
		<set name="crystal_type" val="b" />
		<set name="material" val="blood_steel" />
		<set name="weight" val="480" />
		<set name="price" val="419000" />
		<set name="enchant_enabled" val="1" />
		<cond msgId="1518">
			<player races="Human,Elf,DarkElf,Orc,Dwarf" />
		</cond>
		<for>
			<sub order="0x10" stat="rEvas" val="8" />
			<set order="0x08" stat="rShld" val="20" />
			<set order="0x08" stat="sDef" val="216" />
			<enchant val="0" order="0x0C" stat="sDef" />
		</for>
	</item>
	<item id="670" type="Armor" name="브레이즈 쉴드">
		<set name="icon" val="icon.shield_shield_of_assistance_i00" />
		<set name="default_action" val="equip" />
		<set name="bodypart" val="lhand" />
		<set name="immediate_effect" val="1" />
		<set name="crystal_count" val="112" />
		<set name="crystal_type" val="b" />
		<set name="material" val="chrysolite" />
		<set name="weight" val="560" />
		<set name="price" val="649800" />
		<set name="enchant_enabled" val="1" />
		<cond msgId="1518">
			<player races="Human,Elf,DarkElf,Orc,Dwarf" />
		</cond>
		<for>
			<sub order="0x10" stat="rEvas" val="8" />
			<set order="0x08" stat="rShld" val="20" />
			<set order="0x08" stat="sDef" val="230" />
			<enchant val="0" order="0x0C" stat="sDef" />
		</for>
	</item>
	<item id="671" type="Armor" name="블러드 쉴드">
		<set name="icon" val="icon.shield_knight_shield_i00" />
		<set name="default_action" val="equip" />
		<set name="bodypart" val="lhand" />
		<set name="immediate_effect" val="1" />
		<set name="crystal_count" val="72" />
		<set name="crystal_type" val="b" />
		<set name="material" val="blood_steel" />
		<set name="weight" val="480" />
		<set name="price" val="419000" />
		<set name="enchant_enabled" val="1" />
		<cond msgId="1518">
			<player races="Human,Elf,DarkElf,Orc,Dwarf" />
		</cond>
		<for>
			<sub order="0x10" stat="rEvas" val="8" />
			<set order="0x08" stat="rShld" val="20" />
			<set order="0x08" stat="sDef" val="216" />
			<enchant val="0" order="0x0C" stat="sDef" />
		</for>
	</item>
	<item id="672" type="Armor" name="앱솔루트 쉴드">
		<set name="icon" val="icon.shield_knight_shield_i00" />
		<set name="default_action" val="equip" />
		<set name="bodypart" val="lhand" />
		<set name="immediate_effect" val="1" />
		<set name="crystal_count" val="112" />
		<set name="crystal_type" val="b" />
		<set name="material" val="mithril" />
		<set name="weight" val="560" />
		<set name="price" val="649800" />
		<set name="enchant_enabled" val="1" />
		<cond msgId="1518">
			<player races="Human,Elf,DarkElf,Orc,Dwarf" />
		</cond>
		<for>
			<sub order="0x10" stat="rEvas" val="8" />
			<set order="0x08" stat="rShld" val="20" />
			<set order="0x08" stat="sDef" val="230" />
			<enchant val="0" order="0x0C" stat="sDef" />
		</for>
	</item>
	<item id="673" type="Armor" name="아바돈 쉴드">
		<set name="icon" val="icon.shield_avadon_shield_i00" />
		<set name="default_action" val="equip" />
		<set name="bodypart" val="lhand" />
		<set name="immediate_effect" val="1" />
		<set name="crystal_count" val="56" />
		<set name="crystal_type" val="b" />
		<set name="material" val="damascus" />
		<set name="weight" val="1210" />
		<set name="price" val="419000" />
		<set name="enchant_enabled" val="1" />
		<cond msgId="1518">
			<player races="Human,Elf,DarkElf,Orc,Dwarf" />
		</cond>
		<for>
			<sub order="0x10" stat="rEvas" val="8" />
			<set order="0x08" stat="rShld" val="20" />
			<set order="0x08" stat="sDef" val="216" />
			<enchant val="0" order="0x0C" stat="sDef" />
		</for>
	</item>
	<item id="674" type="Armor" name="디바인 쉴드">
		<set name="icon" val="icon.shield_knight_shield_i00" />
		<set name="default_action" val="equip" />
		<set name="bodypart" val="lhand" />
		<set name="immediate_effect" val="1" />
		<set name="crystal_count" val="112" />
		<set name="crystal_type" val="b" />
		<set name="material" val="adamantaite" />
		<set name="weight" val="560" />
		<set name="price" val="649800" />
		<set name="enchant_enabled" val="1" />
		<cond msgId="1518">
			<player races="Human,Elf,DarkElf,Orc,Dwarf" />
		</cond>
		<for>
			<sub order="0x10" stat="rEvas" val="8" />
			<set order="0x08" stat="rShld" val="20" />
			<set order="0x08" stat="sDef" val="230" />
			<enchant val="0" order="0x0C" stat="sDef" />
		</for>
	</item>
	<item id="675" type="Armor" name="견사 속옷세트">
		<set name="icon" val="icon.armor_underwear01" />
		<set name="default_action" val="equip" />
		<set name="bodypart" val="underwear" />
		<set name="immediate_effect" val="1" />
		<set name="material" val="cloth" />
		<set name="weight" val="170" />
		<set name="price" val="1330" />
		<for>
			<add order="0x10" stat="pDef" val="6" />
		</for>
	</item>
	<item id="676" type="Armor" name="순백의 속옷 세트">
		<set name="icon" val="icon.armor_underwear01" />
		<set name="default_action" val="equip" />
		<set name="bodypart" val="underwear" />
		<set name="immediate_effect" val="1" />
		<set name="material" val="cloth" />
		<set name="weight" val="160" />
		<set name="price" val="6150" />
		<for>
			<add order="0x10" stat="pDef" val="9" />
		</for>
	</item>
	<item id="677" type="Armor" name="원피스 수영복 세트">
		<set name="icon" val="icon.armor_underwear01" />
		<set name="default_action" val="equip" />
		<set name="bodypart" val="underwear" />
		<set name="immediate_effect" val="1" />
		<set name="crystal_count" val="18" />
		<set name="crystal_type" val="d" />
		<set name="material" val="cloth" />
		<set name="weight" val="150" />
		<set name="price" val="10400" />
		<set name="enchant_enabled" val="1" />
		<for>
			<add order="0x10" stat="pDef" val="10" />
			<enchant order="0x0C" stat="pDef" val="0" />
		</for>
	</item>
	<item id="678" type="Armor" name="비키니 수영복 세트">
		<set name="icon" val="icon.armor_underwear02" />
		<set name="default_action" val="equip" />
		<set name="bodypart" val="underwear" />
		<set name="immediate_effect" val="1" />
		<set name="crystal_count" val="30" />
		<set name="crystal_type" val="d" />
		<set name="material" val="cloth" />
		<set name="weight" val="150" />
		<set name="price" val="16700" />
		<set name="enchant_enabled" val="1" />
		<for>
			<add order="0x10" stat="pDef" val="11" />
			<enchant order="0x0C" stat="pDef" val="0" />
		</for>
	</item>
	<item id="679" type="Armor" name="저주받은 속옷 세트">
		<set name="icon" val="icon.armor_underwear01" />
		<set name="default_action" val="equip" />
		<set name="bodypart" val="underwear" />
		<set name="immediate_effect" val="1" />
		<set name="crystal_count" val="46" />
		<set name="crystal_type" val="d" />
		<set name="material" val="cloth" />
		<set name="weight" val="150" />
		<set name="price" val="25400" />
		<set name="enchant_enabled" val="1" />
		<for>
			<add order="0x10" stat="pDef" val="12" />
			<enchant order="0x0C" stat="pDef" val="0" />
		</for>
	</item>
	<item id="680" type="Armor" name="미스릴 속옷 세트">
		<set name="icon" val="icon.armor_underwear01" />
		<set name="default_action" val="equip" />
		<set name="bodypart" val="underwear" />
		<set name="immediate_effect" val="1" />
		<set name="crystal_count" val="25" />
		<set name="crystal_type" val="c" />
		<set name="material" val="mithril" />
		<set name="weight" val="140" />
		<set name="price" val="63100" />
		<set name="enchant_enabled" val="1" />
		<for>
			<add order="0x10" stat="pDef" val="16" />
			<enchant order="0x0C" stat="pDef" val="0" />
		</for>
	</item>
	<item id="681" type="Armor" name="매혹의 속옷 세트">
		<set name="icon" val="icon.armor_underwear01" />
		<set name="default_action" val="equip" />
		<set name="bodypart" val="underwear" />
		<set name="immediate_effect" val="1" />
		<set name="crystal_count" val="32" />
		<set name="crystal_type" val="c" />
		<set name="material" val="cloth" />
		<set name="weight" val="140" />
		<set name="price" val="80500" />
		<set name="enchant_enabled" val="1" />
		<for>
			<add order="0x10" stat="pDef" val="17" />
			<enchant order="0x0C" stat="pDef" val="0" />
		</for>
	</item>
	<item id="682" type="Armor" name="악마의 속옷 세트">
		<set name="icon" val="icon.armor_underwear01" />
		<set name="default_action" val="equip" />
		<set name="bodypart" val="underwear" />
		<set name="immediate_effect" val="1" />
		<set name="crystal_count" val="71" />
		<set name="crystal_type" val="c" />
		<set name="material" val="cloth" />
		<set name="weight" val="140" />
		<set name="price" val="179000" />
		<set name="enchant_enabled" val="1" />
		<for>
			<add order="0x10" stat="pDef" val="19" />
			<enchant order="0x0C" stat="pDef" val="0" />
		</for>
	</item>
	<item id="683" type="Armor" name="신성한 속옷 세트">
		<set name="icon" val="icon.armor_underwear01" />
		<set name="default_action" val="equip" />
		<set name="bodypart" val="underwear" />
		<set name="immediate_effect" val="1" />
		<set name="crystal_count" val="53" />
		<set name="crystal_type" val="b" />
		<set name="material" val="cloth" />
		<set name="weight" val="140" />
		<set name="price" val="402000" />
		<set name="enchant_enabled" val="1" />
		<for>
			<add order="0x10" stat="pDef" val="22" />
			<enchant order="0x0C" stat="pDef" val="0" />
		</for>
	</item>
	<item id="684" type="Armor" name="지배의 수영복 세트">
		<set name="icon" val="icon.armor_underwear02" />
		<set name="default_action" val="equip" />
		<set name="bodypart" val="underwear" />
		<set name="immediate_effect" val="1" />
		<set name="crystal_count" val="70" />
		<set name="crystal_type" val="a" />
		<set name="material" val="cloth" />
		<set name="weight" val="140" />
		<set name="price" val="880000" />
		<set name="enchant_enabled" val="1" />
		<for>
			<add order="0x10" stat="pDef" val="24" />
			<enchant order="0x0C" stat="pDef" val="0" />
		</for>
	</item>
	<item id="685" type="Armor" name="크리스탈 수영복 세트">
		<set name="icon" val="icon.armor_underwear02" />
		<set name="default_action" val="equip" />
		<set name="bodypart" val="underwear" />
		<set name="immediate_effect" val="1" />
		<set name="crystal_count" val="65" />
		<set name="crystal_type" val="s" />
		<set name="material" val="crystal" />
		<set name="weight" val="130" />
		<set name="price" val="1310000" />
		<set name="enchant_enabled" val="1" />
		<for>
			<add order="0x10" stat="pDef" val="26" />
			<enchant order="0x0C" stat="pDef" val="0" />
		</for>
	</item>
	<item id="686" type="EtcItem" name="의자">
		<set name="icon" val="icon.etc_branch_blue_i00" />
		<set name="immediate_effect" val="1" />
		<set name="material" val="wood" />
		<set name="weight" val="100" />
		<set name="price" val="1000" />
	</item>
	<item id="687" type="EtcItem" name="다링의 편지">
		<set name="icon" val="icon.etc_scroll_gray_i00" />
		<set name="immediate_effect" val="1" />
		<set name="material" val="paper" />
		<set name="is_tradable" val="false" />
		<set name="is_dropable" val="false" />
		<set name="is_sellable" val="false" />
		<set name="is_depositable" val="false" />
		<set name="is_questitem" val="true" />
	</item>
	<item id="688" type="EtcItem" name="라푼젤의 손수건">
		<set name="icon" val="icon.etc_piece_of_cloth_white_i00" />
		<set name="immediate_effect" val="1" />
		<set name="material" val="cloth" />
		<set name="is_tradable" val="false" />
		<set name="is_dropable" val="false" />
		<set name="is_sellable" val="false" />
		<set name="is_depositable" val="false" />
		<set name="is_questitem" val="true" />
	</item>
	<item id="689" type="EtcItem" name="아루지엔의 시집">
		<set name="icon" val="icon.etc_spell_books_red_i00" />
		<set name="immediate_effect" val="1" />
		<set name="material" val="paper" />
		<set name="is_tradable" val="false" />
		<set name="is_dropable" val="false" />
		<set name="is_sellable" val="false" />
		<set name="is_depositable" val="false" />
		<set name="is_questitem" val="true" />
	</item>
	<item id="690" type="EtcItem" name="허브티엔의 노래가사집">
		<set name="icon" val="icon.item_normal06" />
		<set name="immediate_effect" val="1" />
		<set name="material" val="paper" />
		<set name="is_tradable" val="false" />
		<set name="is_dropable" val="false" />
		<set name="is_sellable" val="false" />
		<set name="is_depositable" val="false" />
		<set name="is_questitem" val="true" />
	</item>
	<item id="691" type="EtcItem" name="로맨스 소설">
		<set name="icon" val="icon.item_normal07" />
		<set name="immediate_effect" val="1" />
		<set name="material" val="paper" />
		<set name="is_tradable" val="false" />
		<set name="is_dropable" val="false" />
		<set name="is_sellable" val="false" />
		<set name="is_depositable" val="false" />
		<set name="is_questitem" val="true" />
	</item>
	<item id="692" type="EtcItem" name="아루지엔의 편지">
		<set name="icon" val="icon.item_canuse37" />
		<set name="immediate_effect" val="1" />
		<set name="material" val="paper" />
		<set name="is_tradable" val="false" />
		<set name="is_dropable" val="false" />
		<set name="is_sellable" val="false" />
		<set name="is_depositable" val="false" />
		<set name="is_questitem" val="true" />
	</item>
	<item id="693" type="EtcItem" name="그리니스의 편지">
		<set name="icon" val="icon.etc_letter_white_i00" />
		<set name="immediate_effect" val="1" />
		<set name="material" val="paper" />
		<set name="is_tradable" val="false" />
		<set name="is_dropable" val="false" />
		<set name="is_sellable" val="false" />
		<set name="is_depositable" val="false" />
		<set name="is_questitem" val="true" />
	</item>
	<item id="694" type="EtcItem" name="재료목록">
		<set name="icon" val="icon.item_normal37" />
		<set name="immediate_effect" val="1" />
		<set name="material" val="paper" />
		<set name="is_tradable" val="false" />
		<set name="is_dropable" val="false" />
		<set name="is_sellable" val="false" />
		<set name="is_depositable" val="false" />
		<set name="is_questitem" val="true" />
	</item>
	<item id="695" type="EtcItem" name="오닉스 비스트의 피">
		<set name="icon" val="icon.item_canuse48" />
		<set name="immediate_effect" val="1" />
		<set name="material" val="steel" />
		<set name="is_tradable" val="false" />
		<set name="is_dropable" val="false" />
		<set name="is_sellable" val="false" />
		<set name="is_depositable" val="false" />
		<set name="is_stackable" val="true" />
		<set name="is_questitem" val="true" />
	</item>
	<item id="696" type="EtcItem" name="마나 뱀파이어의 허물">
		<set name="icon" val="icon.item_normal30" />
		<set name="immediate_effect" val="1" />
		<set name="material" val="steel" />
		<set name="is_tradable" val="false" />
		<set name="is_dropable" val="false" />
		<set name="is_sellable" val="false" />
		<set name="is_depositable" val="false" />
		<set name="is_stackable" val="true" />
		<set name="is_questitem" val="true" />
	</item>
	<item id="697" type="EtcItem" name="가고일의 뿔">
		<set name="icon" val="icon.item_normal24" />
		<set name="immediate_effect" val="1" />
		<set name="material" val="steel" />
		<set name="is_tradable" val="false" />
		<set name="is_dropable" val="false" />
		<set name="is_sellable" val="false" />
		<set name="is_depositable" val="false" />
		<set name="is_stackable" val="true" />
		<set name="is_questitem" val="true" />
	</item>
	<item id="698" type="EtcItem" name="퇴치 리스트">
		<set name="icon" val="icon.item_normal37" />
		<set name="immediate_effect" val="1" />
		<set name="material" val="steel" />
		<set name="is_tradable" val="false" />
		<set name="is_dropable" val="false" />
		<set name="is_sellable" val="false" />
		<set name="is_depositable" val="false" />
		<set name="is_questitem" val="true" />
	</item>
	<item id="699" type="EtcItem" name="오크의 코">
		<set name="icon" val="icon.item_canuse05" />
		<set name="immediate_effect" val="1" />
		<set name="material" val="steel" />
		<set name="is_tradable" val="false" />
		<set name="is_dropable" val="false" />
		<set name="is_sellable" val="false" />
		<set name="is_depositable" val="false" />
		<set name="is_stackable" val="true" />
		<set name="is_questitem" val="true" />
	</item>
</list>
